README.md
setup.py
spbu/__init__.py
spbu/addresses.py
spbu/classrooms.py
spbu/consts.py
spbu/educators.py
spbu/extracurdivisions.py
spbu/groups.py
spbu/programs.py
spbu/studydivisions.py
spbu/types.py
spbu/util.py
spbuTimetableAPI.egg-info/PKG-INFO
spbuTimetableAPI.egg-info/SOURCES.txt
spbuTimetableAPI.egg-info/dependency_links.txt
spbuTimetableAPI.egg-info/requires.txt
spbuTimetableAPI.egg-info/top_level.txt