Metadata-Version: 1.1
Name: spbuTimetableAPI
Version: 1.0.3
Summary: Python SPbU TimeTable API.
Home-page: https://github.com/EeOneDown/spbuTimetableAPI
Author: EeOneDown
Author-email: st049378@student.spbu.ru
License: GPL2
Download-URL: https://github.com/EeOneDown/spbuTimetableAPI.git
Keywords: spbu timetable api tools
Platform: UNKNOWN
Classifier: Development Status :: 5 - Production/Stable
Classifier: Programming Language :: Python :: 3.7
Classifier: Environment :: Console
Classifier: License :: OSI Approved :: GNU General Public License v2 (GPLv2)
